<annotation>
    <folder>VOC2007</folder>
    <filename>91.JPG</filename>
    <size>
        <width>500</width>
        <height>282</height>
        <depth>3</depth>
    </size>
    <object>
        <name>buoy</name>
        <pose>Unspecified</pose>
        <truncated>0</truncated>
        <difficult>0</difficult>
        <bndbox>
            <xmin>3</xmin>
            <xmax>14</xmax>
            <ymin>63</ymin>
            <ymax>73</ymax>
        </bndbox>
    </object>
    <object>
        <name>other</name>
        <pose>Unspecified</pose>
        <truncated>0</truncated>
        <difficult>0</difficult>
        <bndbox>
            <xmin>331</xmin>
            <xmax>479</xmax>
            <ymin>79</ymin>
            <ymax>101</ymax>
        </bndbox>
    </object>
    <object>
        <name>person</name>
        <pose>Unspecified</pose>
        <truncated>0</truncated>
        <difficult>0</difficult>
        <bndbox>
            <xmin>372</xmin>
            <xmax>395</xmax>
            <ymin>14</ymin>
            <ymax>78</ymax>
        </bndbox>
    </object>
    <object>
        <name>person</name>
        <pose>Unspecified</pose>
        <truncated>0</truncated>
        <difficult>0</difficult>
        <bndbox>
            <xmin>408</xmin>
            <xmax>429</xmax>
            <ymin>17</ymin>
            <ymax>79</ymax>
        </bndbox>
    </object>
    <object>
        <name>boat</name>
        <pose>Unspecified</pose>
        <truncated>0</truncated>
        <difficult>0</difficult>
        <bndbox>
            <xmin>77</xmin>
            <xmax>460</xmax>
            <ymin>136</ymin>
            <ymax>234</ymax>
        </bndbox>
    </object>
</annotation>
